{
  "hisse_kodu": "BIMAS",
  "en_iyi_esik": 0.01,
  "en_iyi_tip": "hibrit",
  "en_iyi_algo": "lgbm",
  "sadece_finansal": {
    "accuracy": 0.432099,
    "wf_acc": 0.486151,
    "f1": 0.148148,
    "f1_macro": 0.361111,
    "esik": 0.5,
    "algoritma": "xgb",
    "wf": {
      "wf_acc_ort": 0.486151,
      "wf_f1_ort": 0.483471,
      "wf_acc_std": 0.034445,
      "wf_f1_std": 0.105253,
      "wf_katlar": 3,
      "wf_detay": [
        {
          "acc": 0.5227,
          "f1": 0.58
        },
        {
          "acc": 0.44,
          "f1": 0.5333
        },
        {
          "acc": 0.4957,
          "f1": 0.3371
        }
      ]
    }
  },
  "hibrit": {
    "accuracy": 0.54321,
    "wf_acc": 0.54763,
    "f1": 0.704,
    "f1_macro": 0.352,
    "esik": 0.3,
    "algoritma": "lgbm",
    "wf": {
      "wf_acc_ort": 0.54763,
      "wf_f1_ort": 0.68879,
      "wf_acc_std": 0.012655,
      "wf_f1_std": 0.035644,
      "wf_katlar": 3,
      "wf_detay": [
        {
          "acc": 0.5455,
          "f1": 0.7059
        },
        {
          "acc": 0.5333,
          "f1": 0.6392
        },
        {
          "acc": 0.5641,
          "f1": 0.7213
        }
      ]
    }
  },
  "iyilesme_acc": 0.111111,
  "iyilesme_f1": -0.009111
}