{
  "hisse_kodu": "KCHOL",
  "en_iyi_esik": 0.01,
  "en_iyi_tip": "finansal",
  "en_iyi_algo": "xgb",
  "sadece_finansal": {
    "accuracy": 0.519481,
    "wf_acc": 0.529344,
    "f1": 0.447761,
    "f1_macro": 0.511237,
    "esik": 0.45,
    "algoritma": "xgb",
    "wf": {
      "wf_acc_ort": 0.529344,
      "wf_f1_ort": 0.399206,
      "wf_acc_std": 0.040221,
      "wf_f1_std": 0.282564,
      "wf_katlar": 3,
      "wf_detay": [
        {
          "acc": 0.4868,
          "f1": 0.0
        },
        {
          "acc": 0.5833,
          "f1": 0.5833
        },
        {
          "acc": 0.5179,
          "f1": 0.6143
        }
      ]
    }
  },
  "hibrit": {
    "accuracy": 0.506494,
    "wf_acc": 0.518431,
    "f1": 0.095238,
    "f1_macro": 0.377976,
    "esik": 0.55,
    "algoritma": "xgb",
    "wf": {
      "wf_acc_ort": 0.518431,
      "wf_f1_ort": 0.231111,
      "wf_acc_std": 0.023148,
      "wf_f1_std": 0.169123,
      "wf_katlar": 3,
      "wf_detay": [
        {
          "acc": 0.4868,
          "f1": 0.0
        },
        {
          "acc": 0.5417,
          "f1": 0.4
        },
        {
          "acc": 0.5268,
          "f1": 0.2933
        }
      ]
    }
  },
  "iyilesme_acc": -0.012987,
  "iyilesme_f1": -0.133261
}