{
  "hisse_kodu": "PETKM",
  "en_iyi_esik": 0.01,
  "en_iyi_tip": "hibrit",
  "en_iyi_algo": "lgbm",
  "sadece_finansal": {
    "accuracy": 0.540541,
    "f1": 0.514286,
    "f1_macro": 0.539194,
    "esik": 0.5,
    "algoritma": "lgbm",
    "wf": {
      "wf_acc_ort": 0.471816,
      "wf_f1_ort": 0.369227,
      "wf_acc_std": 0.032103,
      "wf_f1_std": 0.279447,
      "wf_katlar": 3,
      "wf_detay": [
        {
          "acc": 0.5104,
          "f1": 0.6759
        },
        {
          "acc": 0.4318,
          "f1": 0.4318
        },
        {
          "acc": 0.4732,
          "f1": 0.0
        }
      ]
    }
  },
  "hibrit": {
    "accuracy": 0.581081,
    "f1": 0.666667,
    "f1_macro": 0.551515,
    "esik": 0.45,
    "algoritma": "lgbm",
    "wf": {
      "wf_acc_ort": 0.523223,
      "wf_f1_ort": 0.56007,
      "wf_acc_std": 0.032757,
      "wf_f1_std": 0.081897,
      "wf_katlar": 3,
      "wf_detay": [
        {
          "acc": 0.5104,
          "f1": 0.6759
        },
        {
          "acc": 0.5682,
          "f1": 0.5
        },
        {
          "acc": 0.4911,
          "f1": 0.5043
        }
      ]
    }
  },
  "iyilesme_acc": 0.04054,
  "iyilesme_f1": 0.012321
}